install_texlive/__init__.py
install_texlive/__main__.py
install_texlive/_version.py
install_texlive/parser.py
install_texlive-0.3.7.dist-info/LICENSE
install_texlive-0.3.7.dist-info/METADATA
install_texlive-0.3.7.dist-info/WHEEL
install_texlive-0.3.7.dist-info/entry_points.txt
install_texlive-0.3.7.dist-info/top_level.txt
install_texlive-0.3.7.dist-info/RECORD
