Metadata-Version: 2.1
Name: install-texlive
Version: 0.3.7
Summary: Install texlive without human interaction in the process
Author-email: Maximilian Linhoff <maximilian.linhoff@tu-dortmund.de>
License: MIT License
Project-URL: repository, http://github.com/maxnoe/texlive-batch-installation
Classifier: License :: OSI Approved :: MIT License
Classifier: Development Status :: 5 - Production/Stable
Classifier: Operating System :: POSIX :: Linux
Classifier: Programming Language :: Python :: 3
Classifier: Programming Language :: Python :: 3 :: Only
Classifier: Topic :: Text Processing :: Markup :: LaTeX
Requires-Python: >=3.8
License-File: LICENSE
Requires-Dist: pexpect
Requires-Dist: requests
